{
  "id": "fa9b7cfd-337e-4d14-84f5-d7494fff01d1",
  "prevId": "b197f026-98c6-4054-ac89-be7b4675ed9b",
  "version": "7",
  "dialect": "postgresql",
  "tables": {
    "public.applications": {
      "name": "applications",
      "schema": "",
      "columns": {
        "id": {
          "name": "id",
          "type": "text",
          "primaryKey": true,
          "notNull": true
        },
        "event_id": {
          "name": "event_id",
          "type": "text",
          "primaryKey": false,
          "notNull": true
        },
        "profile_id": {
          "name": "profile_id",
          "type": "text",
          "primaryKey": false,
          "notNull": true
        },
        "status": {
          "name": "status",
          "type": "application_status",
          "typeSchema": "public",
          "primaryKey": false,
          "notNull": true,
          "default": "'submitted'"
        },
        "profile_snapshot": {
          "name": "profile_snapshot",
          "type": "jsonb",
          "primaryKey": false,
          "notNull": true
        },
        "answers": {
          "name": "answers",
          "type": "jsonb",
          "primaryKey": false,
          "notNull": true,
          "default": "'{}'::jsonb"
        },
        "guidelines_acknowledged_at": {
          "name": "guidelines_acknowledged_at",
          "type": "timestamp",
          "primaryKey": false,
          "notNull": false
        },
        "is_block_listed": {
          "name": "is_block_listed",
          "type": "boolean",
          "primaryKey": false,
          "notNull": true,
          "default": false
        },
        "payment_confirmed": {
          "name": "payment_confirmed",
          "type": "boolean",
          "primaryKey": false,
          "notNull": true,
          "default": false
        },
        "pinned": {
          "name": "pinned",
          "type": "boolean",
          "primaryKey": false,
          "notNull": true,
          "default": false
        },
        "response_message": {
          "name": "response_message",
          "type": "text",
          "primaryKey": false,
          "notNull": false
        },
        "created_at": {
          "name": "created_at",
          "type": "timestamp",
          "primaryKey": false,
          "notNull": true,
          "default": "now()"
        },
        "updated_at": {
          "name": "updated_at",
          "type": "timestamp",
          "primaryKey": false,
          "notNull": true,
          "default": "now()"
        }
      },
      "indexes": {
        "applications_profile_id_idx": {
          "name": "applications_profile_id_idx",
          "columns": [
            {
              "expression": "profile_id",
              "isExpression": false,
              "asc": true,
              "nulls": "last"
            }
          ],
          "isUnique": false,
          "concurrently": false,
          "method": "btree",
          "with": {}
        }
      },
      "foreignKeys": {
        "applications_event_id_events_id_fk": {
          "name": "applications_event_id_events_id_fk",
          "tableFrom": "applications",
          "tableTo": "events",
          "columnsFrom": [
            "event_id"
          ],
          "columnsTo": [
            "id"
          ],
          "onDelete": "cascade",
          "onUpdate": "no action"
        },
        "applications_profile_id_profiles_id_fk": {
          "name": "applications_profile_id_profiles_id_fk",
          "tableFrom": "applications",
          "tableTo": "profiles",
          "columnsFrom": [
            "profile_id"
          ],
          "columnsTo": [
            "id"
          ],
          "onDelete": "cascade",
          "onUpdate": "no action"
        }
      },
      "compositePrimaryKeys": {},
      "uniqueConstraints": {
        "applications_event_profile_unique": {
          "name": "applications_event_profile_unique",
          "nullsNotDistinct": false,
          "columns": [
            "event_id",
            "profile_id"
          ]
        }
      },
      "policies": {},
      "checkConstraints": {},
      "isRLSEnabled": false
    },
    "public.artist_profiles": {
      "name": "artist_profiles",
      "schema": "",
      "columns": {
        "id": {
          "name": "id",
          "type": "text",
          "primaryKey": true,
          "notNull": true
        },
        "profile_id": {
          "name": "profile_id",
          "type": "text",
          "primaryKey": false,
          "notNull": true
        },
        "real_name": {
          "name": "real_name",
          "type": "text",
          "primaryKey": false,
          "notNull": false
        },
        "pronouns": {
          "name": "pronouns",
          "type": "text",
          "primaryKey": false,
          "notNull": false
        },
        "contact_email": {
          "name": "contact_email",
          "type": "text",
          "primaryKey": false,
          "notNull": false
        },
        "phone": {
          "name": "phone",
          "type": "text",
          "primaryKey": false,
          "notNull": false
        },
        "bio": {
          "name": "bio",
          "type": "text",
          "primaryKey": false,
          "notNull": false
        },
        "price_range_min_nok": {
          "name": "price_range_min_nok",
          "type": "integer",
          "primaryKey": false,
          "notNull": false
        },
        "price_range_max_nok": {
          "name": "price_range_max_nok",
          "type": "integer",
          "primaryKey": false,
          "notNull": false
        },
        "website_url": {
          "name": "website_url",
          "type": "text",
          "primaryKey": false,
          "notNull": false
        },
        "social_links": {
          "name": "social_links",
          "type": "text",
          "primaryKey": false,
          "notNull": false
        },
        "helpers": {
          "name": "helpers",
          "type": "integer",
          "primaryKey": false,
          "notNull": false,
          "default": 0
        },
        "accessibility_needs": {
          "name": "accessibility_needs",
          "type": "text",
          "primaryKey": false,
          "notNull": false
        },
        "notes": {
          "name": "notes",
          "type": "text",
          "primaryKey": false,
          "notNull": false
        },
        "genres": {
          "name": "genres",
          "type": "text[]",
          "primaryKey": false,
          "notNull": true,
          "default": "'{}'"
        },
        "mediums": {
          "name": "mediums",
          "type": "text[]",
          "primaryKey": false,
          "notNull": true,
          "default": "'{}'"
        },
        "created_at": {
          "name": "created_at",
          "type": "timestamp",
          "primaryKey": false,
          "notNull": true,
          "default": "now()"
        },
        "updated_at": {
          "name": "updated_at",
          "type": "timestamp",
          "primaryKey": false,
          "notNull": true,
          "default": "now()"
        }
      },
      "indexes": {},
      "foreignKeys": {
        "artist_profiles_profile_id_profiles_id_fk": {
          "name": "artist_profiles_profile_id_profiles_id_fk",
          "tableFrom": "artist_profiles",
          "tableTo": "profiles",
          "columnsFrom": [
            "profile_id"
          ],
          "columnsTo": [
            "id"
          ],
          "onDelete": "cascade",
          "onUpdate": "no action"
        }
      },
      "compositePrimaryKeys": {},
      "uniqueConstraints": {
        "artist_profiles_profile_id_unique": {
          "name": "artist_profiles_profile_id_unique",
          "nullsNotDistinct": false,
          "columns": [
            "profile_id"
          ]
        }
      },
      "policies": {},
      "checkConstraints": {},
      "isRLSEnabled": false
    },
    "public.accounts": {
      "name": "accounts",
      "schema": "",
      "columns": {
        "user_id": {
          "name": "user_id",
          "type": "text",
          "primaryKey": false,
          "notNull": true
        },
        "type": {
          "name": "type",
          "type": "text",
          "primaryKey": false,
          "notNull": true
        },
        "provider": {
          "name": "provider",
          "type": "text",
          "primaryKey": false,
          "notNull": true
        },
        "provider_account_id": {
          "name": "provider_account_id",
          "type": "text",
          "primaryKey": false,
          "notNull": true
        },
        "refresh_token": {
          "name": "refresh_token",
          "type": "text",
          "primaryKey": false,
          "notNull": false
        },
        "access_token": {
          "name": "access_token",
          "type": "text",
          "primaryKey": false,
          "notNull": false
        },
        "expires_at": {
          "name": "expires_at",
          "type": "integer",
          "primaryKey": false,
          "notNull": false
        },
        "token_type": {
          "name": "token_type",
          "type": "text",
          "primaryKey": false,
          "notNull": false
        },
        "scope": {
          "name": "scope",
          "type": "text",
          "primaryKey": false,
          "notNull": false
        },
        "id_token": {
          "name": "id_token",
          "type": "text",
          "primaryKey": false,
          "notNull": false
        },
        "session_state": {
          "name": "session_state",
          "type": "text",
          "primaryKey": false,
          "notNull": false
        }
      },
      "indexes": {},
      "foreignKeys": {
        "accounts_user_id_users_id_fk": {
          "name": "accounts_user_id_users_id_fk",
          "tableFrom": "accounts",
          "tableTo": "users",
          "columnsFrom": [
            "user_id"
          ],
          "columnsTo": [
            "id"
          ],
          "onDelete": "cascade",
          "onUpdate": "no action"
        }
      },
      "compositePrimaryKeys": {
        "accounts_provider_provider_account_id_pk": {
          "name": "accounts_provider_provider_account_id_pk",
          "columns": [
            "provider",
            "provider_account_id"
          ]
        }
      },
      "uniqueConstraints": {},
      "policies": {},
      "checkConstraints": {},
      "isRLSEnabled": false
    },
    "public.sessions": {
      "name": "sessions",
      "schema": "",
      "columns": {
        "session_token": {
          "name": "session_token",
          "type": "text",
          "primaryKey": true,
          "notNull": true
        },
        "user_id": {
          "name": "user_id",
          "type": "text",
          "primaryKey": false,
          "notNull": true
        },
        "expires": {
          "name": "expires",
          "type": "timestamp",
          "primaryKey": false,
          "notNull": true
        }
      },
      "indexes": {},
      "foreignKeys": {
        "sessions_user_id_users_id_fk": {
          "name": "sessions_user_id_users_id_fk",
          "tableFrom": "sessions",
          "tableTo": "users",
          "columnsFrom": [
            "user_id"
          ],
          "columnsTo": [
            "id"
          ],
          "onDelete": "cascade",
          "onUpdate": "no action"
        }
      },
      "compositePrimaryKeys": {},
      "uniqueConstraints": {},
      "policies": {},
      "checkConstraints": {},
      "isRLSEnabled": false
    },
    "public.users": {
      "name": "users",
      "schema": "",
      "columns": {
        "id": {
          "name": "id",
          "type": "text",
          "primaryKey": true,
          "notNull": true
        },
        "name": {
          "name": "name",
          "type": "text",
          "primaryKey": false,
          "notNull": false
        },
        "email": {
          "name": "email",
          "type": "text",
          "primaryKey": false,
          "notNull": true
        },
        "email_verified": {
          "name": "email_verified",
          "type": "timestamp",
          "primaryKey": false,
          "notNull": false
        },
        "image": {
          "name": "image",
          "type": "text",
          "primaryKey": false,
          "notNull": false
        },
        "password": {
          "name": "password",
          "type": "text",
          "primaryKey": false,
          "notNull": false
        }
      },
      "indexes": {},
      "foreignKeys": {},
      "compositePrimaryKeys": {},
      "uniqueConstraints": {
        "users_email_unique": {
          "name": "users_email_unique",
          "nullsNotDistinct": false,
          "columns": [
            "email"
          ]
        }
      },
      "policies": {},
      "checkConstraints": {},
      "isRLSEnabled": false
    },
    "public.verification_tokens": {
      "name": "verification_tokens",
      "schema": "",
      "columns": {
        "identifier": {
          "name": "identifier",
          "type": "text",
          "primaryKey": false,
          "notNull": true
        },
        "token": {
          "name": "token",
          "type": "text",
          "primaryKey": false,
          "notNull": true
        },
        "expires": {
          "name": "expires",
          "type": "timestamp",
          "primaryKey": false,
          "notNull": true
        }
      },
      "indexes": {},
      "foreignKeys": {},
      "compositePrimaryKeys": {
        "verification_tokens_identifier_token_pk": {
          "name": "verification_tokens_identifier_token_pk",
          "columns": [
            "identifier",
            "token"
          ]
        }
      },
      "uniqueConstraints": {},
      "policies": {},
      "checkConstraints": {},
      "isRLSEnabled": false
    },
    "public.convention_artist_lists": {
      "name": "convention_artist_lists",
      "schema": "",
      "columns": {
        "id": {
          "name": "id",
          "type": "text",
          "primaryKey": true,
          "notNull": true
        },
        "convention_id": {
          "name": "convention_id",
          "type": "text",
          "primaryKey": false,
          "notNull": true
        },
        "profile_id": {
          "name": "profile_id",
          "type": "text",
          "primaryKey": false,
          "notNull": true
        },
        "list_type": {
          "name": "list_type",
          "type": "list_type",
          "typeSchema": "public",
          "primaryKey": false,
          "notNull": true
        },
        "created_at": {
          "name": "created_at",
          "type": "timestamp",
          "primaryKey": false,
          "notNull": true,
          "default": "now()"
        }
      },
      "indexes": {},
      "foreignKeys": {
        "convention_artist_lists_convention_id_conventions_id_fk": {
          "name": "convention_artist_lists_convention_id_conventions_id_fk",
          "tableFrom": "convention_artist_lists",
          "tableTo": "conventions",
          "columnsFrom": [
            "convention_id"
          ],
          "columnsTo": [
            "id"
          ],
          "onDelete": "cascade",
          "onUpdate": "no action"
        },
        "convention_artist_lists_profile_id_profiles_id_fk": {
          "name": "convention_artist_lists_profile_id_profiles_id_fk",
          "tableFrom": "convention_artist_lists",
          "tableTo": "profiles",
          "columnsFrom": [
            "profile_id"
          ],
          "columnsTo": [
            "id"
          ],
          "onDelete": "cascade",
          "onUpdate": "no action"
        }
      },
      "compositePrimaryKeys": {},
      "uniqueConstraints": {
        "convention_artist_lists_convention_profile_unique": {
          "name": "convention_artist_lists_convention_profile_unique",
          "nullsNotDistinct": false,
          "columns": [
            "convention_id",
            "profile_id"
          ]
        }
      },
      "policies": {},
      "checkConstraints": {},
      "isRLSEnabled": false
    },
    "public.convention_follows": {
      "name": "convention_follows",
      "schema": "",
      "columns": {
        "id": {
          "name": "id",
          "type": "text",
          "primaryKey": true,
          "notNull": true
        },
        "profile_id": {
          "name": "profile_id",
          "type": "text",
          "primaryKey": false,
          "notNull": true
        },
        "convention_id": {
          "name": "convention_id",
          "type": "text",
          "primaryKey": false,
          "notNull": true
        },
        "created_at": {
          "name": "created_at",
          "type": "timestamp",
          "primaryKey": false,
          "notNull": true,
          "default": "now()"
        }
      },
      "indexes": {},
      "foreignKeys": {
        "convention_follows_profile_id_profiles_id_fk": {
          "name": "convention_follows_profile_id_profiles_id_fk",
          "tableFrom": "convention_follows",
          "tableTo": "profiles",
          "columnsFrom": [
            "profile_id"
          ],
          "columnsTo": [
            "id"
          ],
          "onDelete": "cascade",
          "onUpdate": "no action"
        },
        "convention_follows_convention_id_conventions_id_fk": {
          "name": "convention_follows_convention_id_conventions_id_fk",
          "tableFrom": "convention_follows",
          "tableTo": "conventions",
          "columnsFrom": [
            "convention_id"
          ],
          "columnsTo": [
            "id"
          ],
          "onDelete": "cascade",
          "onUpdate": "no action"
        }
      },
      "compositePrimaryKeys": {},
      "uniqueConstraints": {
        "convention_follows_profile_convention_unique": {
          "name": "convention_follows_profile_convention_unique",
          "nullsNotDistinct": false,
          "columns": [
            "profile_id",
            "convention_id"
          ]
        }
      },
      "policies": {},
      "checkConstraints": {},
      "isRLSEnabled": false
    },
    "public.conventions": {
      "name": "conventions",
      "schema": "",
      "columns": {
        "id": {
          "name": "id",
          "type": "text",
          "primaryKey": true,
          "notNull": true
        },
        "organizer_id": {
          "name": "organizer_id",
          "type": "text",
          "primaryKey": false,
          "notNull": true
        },
        "name": {
          "name": "name",
          "type": "text",
          "primaryKey": false,
          "notNull": true
        },
        "description": {
          "name": "description",
          "type": "text",
          "primaryKey": false,
          "notNull": false
        },
        "website_url": {
          "name": "website_url",
          "type": "text",
          "primaryKey": false,
          "notNull": false
        },
        "logo_path": {
          "name": "logo_path",
          "type": "text",
          "primaryKey": false,
          "notNull": false
        },
        "guidelines": {
          "name": "guidelines",
          "type": "text",
          "primaryKey": false,
          "notNull": false
        },
        "acceptance_message": {
          "name": "acceptance_message",
          "type": "text",
          "primaryKey": false,
          "notNull": false
        },
        "rejection_message": {
          "name": "rejection_message",
          "type": "text",
          "primaryKey": false,
          "notNull": false
        },
        "waitlist_enabled": {
          "name": "waitlist_enabled",
          "type": "boolean",
          "primaryKey": false,
          "notNull": true,
          "default": false
        },
        "created_at": {
          "name": "created_at",
          "type": "timestamp",
          "primaryKey": false,
          "notNull": true,
          "default": "now()"
        },
        "updated_at": {
          "name": "updated_at",
          "type": "timestamp",
          "primaryKey": false,
          "notNull": true,
          "default": "now()"
        }
      },
      "indexes": {},
      "foreignKeys": {
        "conventions_organizer_id_profiles_id_fk": {
          "name": "conventions_organizer_id_profiles_id_fk",
          "tableFrom": "conventions",
          "tableTo": "profiles",
          "columnsFrom": [
            "organizer_id"
          ],
          "columnsTo": [
            "id"
          ],
          "onDelete": "cascade",
          "onUpdate": "no action"
        }
      },
      "compositePrimaryKeys": {},
      "uniqueConstraints": {
        "conventions_organizer_id_unique": {
          "name": "conventions_organizer_id_unique",
          "nullsNotDistinct": false,
          "columns": [
            "organizer_id"
          ]
        }
      },
      "policies": {},
      "checkConstraints": {},
      "isRLSEnabled": false
    },
    "public.event_announcements": {
      "name": "event_announcements",
      "schema": "",
      "columns": {
        "id": {
          "name": "id",
          "type": "text",
          "primaryKey": true,
          "notNull": true
        },
        "event_id": {
          "name": "event_id",
          "type": "text",
          "primaryKey": false,
          "notNull": true
        },
        "author_profile_id": {
          "name": "author_profile_id",
          "type": "text",
          "primaryKey": false,
          "notNull": true
        },
        "subject": {
          "name": "subject",
          "type": "text",
          "primaryKey": false,
          "notNull": true
        },
        "body": {
          "name": "body",
          "type": "text",
          "primaryKey": false,
          "notNull": true
        },
        "created_at": {
          "name": "created_at",
          "type": "timestamp",
          "primaryKey": false,
          "notNull": true,
          "default": "now()"
        },
        "updated_at": {
          "name": "updated_at",
          "type": "timestamp",
          "primaryKey": false,
          "notNull": true,
          "default": "now()"
        }
      },
      "indexes": {
        "event_announcements_event_id_idx": {
          "name": "event_announcements_event_id_idx",
          "columns": [
            {
              "expression": "event_id",
              "isExpression": false,
              "asc": true,
              "nulls": "last"
            }
          ],
          "isUnique": false,
          "concurrently": false,
          "method": "btree",
          "with": {}
        }
      },
      "foreignKeys": {
        "event_announcements_event_id_events_id_fk": {
          "name": "event_announcements_event_id_events_id_fk",
          "tableFrom": "event_announcements",
          "tableTo": "events",
          "columnsFrom": [
            "event_id"
          ],
          "columnsTo": [
            "id"
          ],
          "onDelete": "cascade",
          "onUpdate": "no action"
        },
        "event_announcements_author_profile_id_profiles_id_fk": {
          "name": "event_announcements_author_profile_id_profiles_id_fk",
          "tableFrom": "event_announcements",
          "tableTo": "profiles",
          "columnsFrom": [
            "author_profile_id"
          ],
          "columnsTo": [
            "id"
          ],
          "onDelete": "cascade",
          "onUpdate": "no action"
        }
      },
      "compositePrimaryKeys": {},
      "uniqueConstraints": {},
      "policies": {},
      "checkConstraints": {},
      "isRLSEnabled": false
    },
    "public.event_thread_messages": {
      "name": "event_thread_messages",
      "schema": "",
      "columns": {
        "id": {
          "name": "id",
          "type": "text",
          "primaryKey": true,
          "notNull": true
        },
        "thread_id": {
          "name": "thread_id",
          "type": "text",
          "primaryKey": false,
          "notNull": true
        },
        "author_profile_id": {
          "name": "author_profile_id",
          "type": "text",
          "primaryKey": false,
          "notNull": true
        },
        "body": {
          "name": "body",
          "type": "text",
          "primaryKey": false,
          "notNull": true
        },
        "created_at": {
          "name": "created_at",
          "type": "timestamp",
          "primaryKey": false,
          "notNull": true,
          "default": "now()"
        }
      },
      "indexes": {
        "event_thread_messages_thread_created_idx": {
          "name": "event_thread_messages_thread_created_idx",
          "columns": [
            {
              "expression": "thread_id",
              "isExpression": false,
              "asc": true,
              "nulls": "last"
            },
            {
              "expression": "created_at",
              "isExpression": false,
              "asc": true,
              "nulls": "last"
            }
          ],
          "isUnique": false,
          "concurrently": false,
          "method": "btree",
          "with": {}
        }
      },
      "foreignKeys": {
        "event_thread_messages_thread_id_event_threads_id_fk": {
          "name": "event_thread_messages_thread_id_event_threads_id_fk",
          "tableFrom": "event_thread_messages",
          "tableTo": "event_threads",
          "columnsFrom": [
            "thread_id"
          ],
          "columnsTo": [
            "id"
          ],
          "onDelete": "cascade",
          "onUpdate": "no action"
        },
        "event_thread_messages_author_profile_id_profiles_id_fk": {
          "name": "event_thread_messages_author_profile_id_profiles_id_fk",
          "tableFrom": "event_thread_messages",
          "tableTo": "profiles",
          "columnsFrom": [
            "author_profile_id"
          ],
          "columnsTo": [
            "id"
          ],
          "onDelete": "cascade",
          "onUpdate": "no action"
        }
      },
      "compositePrimaryKeys": {},
      "uniqueConstraints": {},
      "policies": {},
      "checkConstraints": {},
      "isRLSEnabled": false
    },
    "public.event_threads": {
      "name": "event_threads",
      "schema": "",
      "columns": {
        "id": {
          "name": "id",
          "type": "text",
          "primaryKey": true,
          "notNull": true
        },
        "event_id": {
          "name": "event_id",
          "type": "text",
          "primaryKey": false,
          "notNull": true
        },
        "artist_profile_id": {
          "name": "artist_profile_id",
          "type": "text",
          "primaryKey": false,
          "notNull": true
        },
        "last_message_at": {
          "name": "last_message_at",
          "type": "timestamp",
          "primaryKey": false,
          "notNull": true,
          "default": "now()"
        },
        "artist_last_read_at": {
          "name": "artist_last_read_at",
          "type": "timestamp",
          "primaryKey": false,
          "notNull": false
        },
        "organizer_last_read_at": {
          "name": "organizer_last_read_at",
          "type": "timestamp",
          "primaryKey": false,
          "notNull": false
        },
        "created_at": {
          "name": "created_at",
          "type": "timestamp",
          "primaryKey": false,
          "notNull": true,
          "default": "now()"
        },
        "updated_at": {
          "name": "updated_at",
          "type": "timestamp",
          "primaryKey": false,
          "notNull": true,
          "default": "now()"
        }
      },
      "indexes": {
        "event_threads_event_artist_idx": {
          "name": "event_threads_event_artist_idx",
          "columns": [
            {
              "expression": "event_id",
              "isExpression": false,
              "asc": true,
              "nulls": "last"
            },
            {
              "expression": "artist_profile_id",
              "isExpression": false,
              "asc": true,
              "nulls": "last"
            }
          ],
          "isUnique": true,
          "concurrently": false,
          "method": "btree",
          "with": {}
        },
        "event_threads_event_last_message_idx": {
          "name": "event_threads_event_last_message_idx",
          "columns": [
            {
              "expression": "event_id",
              "isExpression": false,
              "asc": true,
              "nulls": "last"
            },
            {
              "expression": "last_message_at",
              "isExpression": false,
              "asc": true,
              "nulls": "last"
            }
          ],
          "isUnique": false,
          "concurrently": false,
          "method": "btree",
          "with": {}
        }
      },
      "foreignKeys": {
        "event_threads_event_id_events_id_fk": {
          "name": "event_threads_event_id_events_id_fk",
          "tableFrom": "event_threads",
          "tableTo": "events",
          "columnsFrom": [
            "event_id"
          ],
          "columnsTo": [
            "id"
          ],
          "onDelete": "cascade",
          "onUpdate": "no action"
        },
        "event_threads_artist_profile_id_profiles_id_fk": {
          "name": "event_threads_artist_profile_id_profiles_id_fk",
          "tableFrom": "event_threads",
          "tableTo": "profiles",
          "columnsFrom": [
            "artist_profile_id"
          ],
          "columnsTo": [
            "id"
          ],
          "onDelete": "cascade",
          "onUpdate": "no action"
        }
      },
      "compositePrimaryKeys": {},
      "uniqueConstraints": {},
      "policies": {},
      "checkConstraints": {},
      "isRLSEnabled": false
    },
    "public.events": {
      "name": "events",
      "schema": "",
      "columns": {
        "id": {
          "name": "id",
          "type": "text",
          "primaryKey": true,
          "notNull": true
        },
        "convention_id": {
          "name": "convention_id",
          "type": "text",
          "primaryKey": false,
          "notNull": true
        },
        "name": {
          "name": "name",
          "type": "text",
          "primaryKey": false,
          "notNull": true
        },
        "description": {
          "name": "description",
          "type": "text",
          "primaryKey": false,
          "notNull": false
        },
        "status": {
          "name": "status",
          "type": "event_status",
          "typeSchema": "public",
          "primaryKey": false,
          "notNull": true,
          "default": "'draft'"
        },
        "event_start_date": {
          "name": "event_start_date",
          "type": "date",
          "primaryKey": false,
          "notNull": true
        },
        "event_end_date": {
          "name": "event_end_date",
          "type": "date",
          "primaryKey": false,
          "notNull": false
        },
        "application_open_date": {
          "name": "application_open_date",
          "type": "date",
          "primaryKey": false,
          "notNull": false
        },
        "application_close_date": {
          "name": "application_close_date",
          "type": "date",
          "primaryKey": false,
          "notNull": false
        },
        "venue_name": {
          "name": "venue_name",
          "type": "text",
          "primaryKey": false,
          "notNull": false
        },
        "venue_address": {
          "name": "venue_address",
          "type": "text",
          "primaryKey": false,
          "notNull": false
        },
        "venue_city": {
          "name": "venue_city",
          "type": "text",
          "primaryKey": false,
          "notNull": false
        },
        "venue_country": {
          "name": "venue_country",
          "type": "text",
          "primaryKey": false,
          "notNull": false
        },
        "map_embed_url": {
          "name": "map_embed_url",
          "type": "text",
          "primaryKey": false,
          "notNull": false
        },
        "available_stands": {
          "name": "available_stands",
          "type": "integer",
          "primaryKey": false,
          "notNull": false
        },
        "table_dimensions": {
          "name": "table_dimensions",
          "type": "text",
          "primaryKey": false,
          "notNull": false
        },
        "price_info": {
          "name": "price_info",
          "type": "text",
          "primaryKey": false,
          "notNull": false
        },
        "setup_time": {
          "name": "setup_time",
          "type": "text",
          "primaryKey": false,
          "notNull": false
        },
        "teardown_time": {
          "name": "teardown_time",
          "type": "text",
          "primaryKey": false,
          "notNull": false
        },
        "amenities": {
          "name": "amenities",
          "type": "jsonb",
          "primaryKey": false,
          "notNull": false
        },
        "field_requirements": {
          "name": "field_requirements",
          "type": "jsonb",
          "primaryKey": false,
          "notNull": false
        },
        "min_portfolio_images": {
          "name": "min_portfolio_images",
          "type": "integer",
          "primaryKey": false,
          "notNull": false
        },
        "acceptance_message": {
          "name": "acceptance_message",
          "type": "text",
          "primaryKey": false,
          "notNull": false
        },
        "rejection_message": {
          "name": "rejection_message",
          "type": "text",
          "primaryKey": false,
          "notNull": false
        },
        "guidelines_override": {
          "name": "guidelines_override",
          "type": "text",
          "primaryKey": false,
          "notNull": false
        },
        "table_size_options": {
          "name": "table_size_options",
          "type": "jsonb",
          "primaryKey": false,
          "notNull": true,
          "default": "'[]'::jsonb"
        },
        "max_assistants": {
          "name": "max_assistants",
          "type": "integer",
          "primaryKey": false,
          "notNull": true,
          "default": 0
        },
        "assistant_fee_nok": {
          "name": "assistant_fee_nok",
          "type": "integer",
          "primaryKey": false,
          "notNull": false
        },
        "floor_plan": {
          "name": "floor_plan",
          "type": "jsonb",
          "primaryKey": false,
          "notNull": false
        },
        "floor_plan_published_at": {
          "name": "floor_plan_published_at",
          "type": "timestamp",
          "primaryKey": false,
          "notNull": false
        },
        "floor_plan_auto_publish_days_before": {
          "name": "floor_plan_auto_publish_days_before",
          "type": "integer",
          "primaryKey": false,
          "notNull": false
        },
        "created_at": {
          "name": "created_at",
          "type": "timestamp",
          "primaryKey": false,
          "notNull": true,
          "default": "now()"
        },
        "updated_at": {
          "name": "updated_at",
          "type": "timestamp",
          "primaryKey": false,
          "notNull": true,
          "default": "now()"
        }
      },
      "indexes": {
        "events_convention_id_idx": {
          "name": "events_convention_id_idx",
          "columns": [
            {
              "expression": "convention_id",
              "isExpression": false,
              "asc": true,
              "nulls": "last"
            }
          ],
          "isUnique": false,
          "concurrently": false,
          "method": "btree",
          "with": {}
        }
      },
      "foreignKeys": {
        "events_convention_id_conventions_id_fk": {
          "name": "events_convention_id_conventions_id_fk",
          "tableFrom": "events",
          "tableTo": "conventions",
          "columnsFrom": [
            "convention_id"
          ],
          "columnsTo": [
            "id"
          ],
          "onDelete": "cascade",
          "onUpdate": "no action"
        }
      },
      "compositePrimaryKeys": {},
      "uniqueConstraints": {},
      "policies": {},
      "checkConstraints": {},
      "isRLSEnabled": false
    },
    "public.profiles": {
      "name": "profiles",
      "schema": "",
      "columns": {
        "id": {
          "name": "id",
          "type": "text",
          "primaryKey": true,
          "notNull": true
        },
        "user_id": {
          "name": "user_id",
          "type": "text",
          "primaryKey": false,
          "notNull": true
        },
        "role": {
          "name": "role",
          "type": "role",
          "typeSchema": "public",
          "primaryKey": false,
          "notNull": true
        },
        "display_name": {
          "name": "display_name",
          "type": "text",
          "primaryKey": false,
          "notNull": true
        },
        "created_at": {
          "name": "created_at",
          "type": "timestamp",
          "primaryKey": false,
          "notNull": true,
          "default": "now()"
        },
        "updated_at": {
          "name": "updated_at",
          "type": "timestamp",
          "primaryKey": false,
          "notNull": true,
          "default": "now()"
        }
      },
      "indexes": {},
      "foreignKeys": {
        "profiles_user_id_users_id_fk": {
          "name": "profiles_user_id_users_id_fk",
          "tableFrom": "profiles",
          "tableTo": "users",
          "columnsFrom": [
            "user_id"
          ],
          "columnsTo": [
            "id"
          ],
          "onDelete": "cascade",
          "onUpdate": "no action"
        }
      },
      "compositePrimaryKeys": {},
      "uniqueConstraints": {
        "profiles_user_id_unique": {
          "name": "profiles_user_id_unique",
          "nullsNotDistinct": false,
          "columns": [
            "user_id"
          ]
        }
      },
      "policies": {},
      "checkConstraints": {},
      "isRLSEnabled": false
    },
    "public.notification_preferences": {
      "name": "notification_preferences",
      "schema": "",
      "columns": {
        "id": {
          "name": "id",
          "type": "text",
          "primaryKey": true,
          "notNull": true
        },
        "profile_id": {
          "name": "profile_id",
          "type": "text",
          "primaryKey": false,
          "notNull": true
        },
        "notification_type": {
          "name": "notification_type",
          "type": "notification_type",
          "typeSchema": "public",
          "primaryKey": false,
          "notNull": true
        },
        "email_enabled": {
          "name": "email_enabled",
          "type": "boolean",
          "primaryKey": false,
          "notNull": true,
          "default": false
        }
      },
      "indexes": {},
      "foreignKeys": {
        "notification_preferences_profile_id_profiles_id_fk": {
          "name": "notification_preferences_profile_id_profiles_id_fk",
          "tableFrom": "notification_preferences",
          "tableTo": "profiles",
          "columnsFrom": [
            "profile_id"
          ],
          "columnsTo": [
            "id"
          ],
          "onDelete": "cascade",
          "onUpdate": "no action"
        }
      },
      "compositePrimaryKeys": {},
      "uniqueConstraints": {
        "notification_preferences_profile_type_unique": {
          "name": "notification_preferences_profile_type_unique",
          "nullsNotDistinct": false,
          "columns": [
            "profile_id",
            "notification_type"
          ]
        }
      },
      "policies": {},
      "checkConstraints": {},
      "isRLSEnabled": false
    },
    "public.notifications": {
      "name": "notifications",
      "schema": "",
      "columns": {
        "id": {
          "name": "id",
          "type": "text",
          "primaryKey": true,
          "notNull": true
        },
        "recipient_profile_id": {
          "name": "recipient_profile_id",
          "type": "text",
          "primaryKey": false,
          "notNull": true
        },
        "type": {
          "name": "type",
          "type": "notification_type",
          "typeSchema": "public",
          "primaryKey": false,
          "notNull": true
        },
        "message": {
          "name": "message",
          "type": "text",
          "primaryKey": false,
          "notNull": true
        },
        "link": {
          "name": "link",
          "type": "text",
          "primaryKey": false,
          "notNull": false
        },
        "is_read": {
          "name": "is_read",
          "type": "boolean",
          "primaryKey": false,
          "notNull": true,
          "default": false
        },
        "created_at": {
          "name": "created_at",
          "type": "timestamp",
          "primaryKey": false,
          "notNull": true,
          "default": "now()"
        }
      },
      "indexes": {
        "notifications_recipient_read_idx": {
          "name": "notifications_recipient_read_idx",
          "columns": [
            {
              "expression": "recipient_profile_id",
              "isExpression": false,
              "asc": true,
              "nulls": "last"
            },
            {
              "expression": "is_read",
              "isExpression": false,
              "asc": true,
              "nulls": "last"
            }
          ],
          "isUnique": false,
          "concurrently": false,
          "method": "btree",
          "with": {}
        }
      },
      "foreignKeys": {
        "notifications_recipient_profile_id_profiles_id_fk": {
          "name": "notifications_recipient_profile_id_profiles_id_fk",
          "tableFrom": "notifications",
          "tableTo": "profiles",
          "columnsFrom": [
            "recipient_profile_id"
          ],
          "columnsTo": [
            "id"
          ],
          "onDelete": "cascade",
          "onUpdate": "no action"
        }
      },
      "compositePrimaryKeys": {},
      "uniqueConstraints": {},
      "policies": {},
      "checkConstraints": {},
      "isRLSEnabled": false
    },
    "public.portfolio_images": {
      "name": "portfolio_images",
      "schema": "",
      "columns": {
        "id": {
          "name": "id",
          "type": "text",
          "primaryKey": true,
          "notNull": true
        },
        "profile_id": {
          "name": "profile_id",
          "type": "text",
          "primaryKey": false,
          "notNull": true
        },
        "filename": {
          "name": "filename",
          "type": "text",
          "primaryKey": false,
          "notNull": true
        },
        "storage_path": {
          "name": "storage_path",
          "type": "text",
          "primaryKey": false,
          "notNull": true
        },
        "mime_type": {
          "name": "mime_type",
          "type": "text",
          "primaryKey": false,
          "notNull": true
        },
        "width": {
          "name": "width",
          "type": "integer",
          "primaryKey": false,
          "notNull": false
        },
        "height": {
          "name": "height",
          "type": "integer",
          "primaryKey": false,
          "notNull": false
        },
        "sort_order": {
          "name": "sort_order",
          "type": "integer",
          "primaryKey": false,
          "notNull": true,
          "default": 0
        },
        "section": {
          "name": "section",
          "type": "portfolio_section",
          "typeSchema": "public",
          "primaryKey": false,
          "notNull": true,
          "default": "'product'"
        },
        "caption": {
          "name": "caption",
          "type": "text",
          "primaryKey": false,
          "notNull": false
        },
        "created_at": {
          "name": "created_at",
          "type": "timestamp",
          "primaryKey": false,
          "notNull": true,
          "default": "now()"
        }
      },
      "indexes": {},
      "foreignKeys": {
        "portfolio_images_profile_id_profiles_id_fk": {
          "name": "portfolio_images_profile_id_profiles_id_fk",
          "tableFrom": "portfolio_images",
          "tableTo": "profiles",
          "columnsFrom": [
            "profile_id"
          ],
          "columnsTo": [
            "id"
          ],
          "onDelete": "cascade",
          "onUpdate": "no action"
        }
      },
      "compositePrimaryKeys": {},
      "uniqueConstraints": {},
      "policies": {},
      "checkConstraints": {},
      "isRLSEnabled": false
    }
  },
  "enums": {
    "public.application_status": {
      "name": "application_status",
      "schema": "public",
      "values": [
        "submitted",
        "under_review",
        "accepted",
        "rejected",
        "revoked",
        "waitlisted"
      ]
    },
    "public.list_type": {
      "name": "list_type",
      "schema": "public",
      "values": [
        "allow",
        "block"
      ]
    },
    "public.event_status": {
      "name": "event_status",
      "schema": "public",
      "values": [
        "draft",
        "published",
        "accepting_applications",
        "reviewing",
        "results_published"
      ]
    },
    "public.role": {
      "name": "role",
      "schema": "public",
      "values": [
        "artist",
        "organizer"
      ]
    },
    "public.notification_type": {
      "name": "notification_type",
      "schema": "public",
      "values": [
        "event_published",
        "event_opened",
        "new_event",
        "results_published",
        "application_revoked",
        "new_application",
        "event_announcement",
        "thread_message_from_artist",
        "thread_message_from_organizer"
      ]
    },
    "public.portfolio_section": {
      "name": "portfolio_section",
      "schema": "public",
      "values": [
        "promo",
        "product",
        "previous_stand"
      ]
    }
  },
  "schemas": {},
  "sequences": {},
  "roles": {},
  "policies": {},
  "views": {},
  "_meta": {
    "columns": {},
    "schemas": {},
    "tables": {}
  }
}